cwe2/__init__.py
cwe2/database.py
cwe2/mappings.py
cwe2/weakness.py
cwe2/database_v49/__init__.py
cwe2/database_v49/cwe-tou.LICENSE
cwe2/database_v49/cwe.ABOUT
cwe2/database_v49/cwe.NOTICE
cwe2/database_v49/cwec_v4.14.xml
cwe2/database_v49/external_mappings/1008.csv
cwe2/database_v49/external_mappings/1133.csv
cwe2/database_v49/external_mappings/1154.csv
cwe2/database_v49/external_mappings/1178.csv
cwe2/database_v49/external_mappings/1305.csv
cwe2/database_v49/external_mappings/1340.csv
cwe2/database_v49/external_mappings/1343.csv
cwe2/database_v49/external_mappings/1344.csv
cwe2/database_v49/external_mappings/1358.csv
cwe2/database_v49/external_mappings/1424.csv
cwe2/database_v49/external_mappings/1425.csv
cwe2/database_v49/external_mappings/700.csv
cwe2/database_v49/external_mappings/888.csv
cwe2/database_v49/helpful_views/1003.csv
cwe2/database_v49/helpful_views/1040.csv
cwe2/database_v49/helpful_views/1081.csv
cwe2/database_v49/helpful_views/1400.csv
cwe2/database_v49/helpful_views/2000.csv
cwe2/database_v49/helpful_views/604.csv
cwe2/database_v49/helpful_views/658.csv
cwe2/database_v49/helpful_views/659.csv
cwe2/database_v49/helpful_views/660.csv
cwe2/database_v49/helpful_views/661.csv
cwe2/database_v49/helpful_views/677.csv
cwe2/database_v49/helpful_views/678.csv
cwe2/database_v49/helpful_views/701.csv
cwe2/database_v49/helpful_views/702.csv
cwe2/database_v49/helpful_views/709.csv
cwe2/database_v49/helpful_views/884.csv
cwe2/database_v49/helpful_views/919.csv
cwe2/database_v49/navigate_cwe/1000.csv
cwe2/database_v49/navigate_cwe/1194.csv
cwe2/database_v49/navigate_cwe/699.csv
cwe2/database_v49/obsolete_views/1026.csv
cwe2/database_v49/obsolete_views/1128.csv
cwe2/database_v49/obsolete_views/1200.csv
cwe2/database_v49/obsolete_views/1337.csv
cwe2/database_v49/obsolete_views/1350.csv
cwe2/database_v49/obsolete_views/1387.csv
cwe2/database_v49/obsolete_views/629.csv
cwe2/database_v49/obsolete_views/635.csv
cwe2/database_v49/obsolete_views/711.csv
cwe2-3.0.0.dist-info/CHANGELOG.rst
cwe2-3.0.0.dist-info/METADATA
cwe2-3.0.0.dist-info/WHEEL
cwe2-3.0.0.dist-info/cwe-tou.LICENSE
cwe2-3.0.0.dist-info/mit.LICENSE
cwe2-3.0.0.dist-info/top_level.txt
cwe2-3.0.0.dist-info/RECORD
