Metadata-Version: 2.1
Name: cwe2
Version: 3.0.0
Summary: cwe2 is a CWE common weakness enumeration library for Python
Home-page: https://github.com/nexB/cwe2
Author: Ziad Hany, nexB. Inc. and others. Originally based on Julian Nash cwe.
Author-email: info@aboutcode.org
License: MIT and LicenseRef-scancode-cwe-tou
Keywords: utilities,CWE,weakness,CVE,vulnerabilities
Classifier: Development Status :: 5 - Production/Stable
Classifier: Intended Audience :: Developers
Classifier: Programming Language :: Python :: 3
Classifier: Programming Language :: Python :: 3 :: Only
Classifier: Topic :: Software Development
Classifier: Topic :: Utilities
Requires-Python: >=3.7
License-File: mit.LICENSE
License-File: cwe-tou.LICENSE
License-File: CHANGELOG.rst
Requires-Dist: importlib-resources >=5.10.2
Provides-Extra: docs
Requires-Dist: Sphinx >=5.0.2 ; extra == 'docs'
Requires-Dist: sphinx-rtd-theme >=1.0.0 ; extra == 'docs'
Requires-Dist: sphinx-reredirects >=0.1.2 ; extra == 'docs'
Requires-Dist: doc8 >=0.11.2 ; extra == 'docs'
Provides-Extra: testing
Requires-Dist: pytest !=7.0.0,>=6 ; extra == 'testing'
Requires-Dist: pytest-xdist >=2 ; extra == 'testing'
Requires-Dist: aboutcode-toolkit >=6.0.0 ; extra == 'testing'
Requires-Dist: pycodestyle >=2.8.0 ; extra == 'testing'
Requires-Dist: black >=22.3.0 ; extra == 'testing'
Requires-Dist: isort >=5.10.1 ; extra == 'testing'
Requires-Dist: doc8 >=0.11.1 ; extra == 'testing'
